migipo/__init__.py
migipo/cli/__init__.py
migipo/cli/cli.py
migipo/core/__init__.py
migipo/core/_commands.py
migipo/core/_load.py
migipo-0.0.1.dist-info/licenses/LICENSE
migipo-0.0.1.dist-info/METADATA
migipo-0.0.1.dist-info/WHEEL
migipo-0.0.1.dist-info/entry_points.txt
migipo-0.0.1.dist-info/top_level.txt
migipo-0.0.1.dist-info/RECORD
