Metadata-Version: 2.4
Name: migipo
Version: 0.0.1
Summary: Mirror a Git Repo
Author-email: Adwaith-Rajesh <me@adwaith.dev>
License-Expression: MIT
Project-URL: Homepage, https://github.com/Adwaith-Rajesh/migipo
Classifier: Programming Language :: Python :: 3
Classifier: Operating System :: OS Independent
Requires-Python: >=3.12
License-File: LICENSE
Requires-Dist: argcomplete>=3.6.2
Requires-Dist: typeguard>=4.4.2
Dynamic: license-file
